heartbeat_status/__init__.py
heartbeat_status/actions.py
heartbeat_status/deta.py
heartbeat_status/fitbit.py
heartbeat_status/graphs.py
heartbeat_status/main.py
heartbeat_status/models.py
heartbeat_status/py.typed
heartbeat_status/static_files/favicon.ico
heartbeat_status/static_files/favicon.jpg
heartbeat_status/static_files/favicon.png
heartbeat_status/static_files/index.css
heartbeat_status/static_files/spinner.gif
heartbeat_status/templates/index.j2
heartbeat_status-0.0.4.dist-info/LICENSE.txt
heartbeat_status-0.0.4.dist-info/METADATA
heartbeat_status-0.0.4.dist-info/WHEEL
heartbeat_status-0.0.4.dist-info/entry_points.txt
heartbeat_status-0.0.4.dist-info/RECORD
