Metadata-Version: 2.1
Name: heartbeat-status
Version: 0.0.4
Summary: Check Fitbit heartbeat status online
Home-page: https://github.com/eggplants/heartbeat-status
License: MIT
Keywords: fitbit
Author: eggplants
Author-email: w10776e8w@yahoo.co.jp
Requires-Python: >=3.9,<4
Classifier: License :: OSI Approved :: MIT License
Classifier: Programming Language :: Python
Classifier: Programming Language :: Python :: 3
Classifier: Programming Language :: Python :: 3.9
Classifier: Programming Language :: Python :: 3.10
Classifier: Programming Language :: Python :: 3.11
Classifier: Programming Language :: Python :: 3.12
Classifier: Programming Language :: Python :: 3 :: Only
Classifier: Programming Language :: Python :: Implementation :: CPython
Requires-Dist: deta (>=1.2.0,<2.0.0)
Requires-Dist: jinja2 (>=3.1.2,<4.0.0)
Requires-Dist: pandas (>=2.1.4,<3.0.0)
Requires-Dist: pandas-stubs (>=2.1.1.230928,<3.0.0.0)
Requires-Dist: plotly (>=5.18.0,<6.0.0)
Requires-Dist: pydantic (>=2.5.2,<3.0.0)
Requires-Dist: python-dotenv (>=1.0.0,<2.0.0)
Requires-Dist: requests (>=2.31.0,<3.0.0)
Requires-Dist: starlette (>=0.37.1,<0.38.0)
Requires-Dist: uvicorn (>=0.24,<0.28)
Project-URL: Repository, https://github.com/eggplants/heartbeat-status
